mcp_server_google_news/__init__.py
mcp_server_google_news/__main__.py
mcp_server_google_news/server.py
mcp_server_google_news-0.1.8.dist-info/METADATA
mcp_server_google_news-0.1.8.dist-info/WHEEL
mcp_server_google_news-0.1.8.dist-info/entry_points.txt
mcp_server_google_news-0.1.8.dist-info/RECORD
