Metadata-Version: 2.4
Name: mcp-server-google-news
Version: 0.1.8
Summary: Google News MCP server for fetching news articles
Author-email: yareyaredesuyo <yareyaredesuyo@gmail.com>
License-Expression: MIT
Keywords: google-news,llm,mcp,model-context-protocol,news,rss
Classifier: Development Status :: 4 - Beta
Classifier: Intended Audience :: Developers
Classifier: License :: OSI Approved :: MIT License
Classifier: Programming Language :: Python :: 3
Classifier: Programming Language :: Python :: 3.10
Classifier: Topic :: Internet :: WWW/HTTP :: Indexing/Search
Classifier: Topic :: Software Development :: Libraries :: Python Modules
Requires-Python: >=3.10
Requires-Dist: fastmcp>=2.5.2
Requires-Dist: feedparser>=6.0.0
Requires-Dist: pydantic>=2.0.0
